gpt_traceback/__init__.py
gpt_traceback/ipython_traceback.py
gpt_traceback/print_exception.py
gpt_traceback/prompt.py
gpt_traceback-0.1.22.dist-info/LICENSE
gpt_traceback-0.1.22.dist-info/METADATA
gpt_traceback-0.1.22.dist-info/WHEEL
gpt_traceback-0.1.22.dist-info/top_level.txt
gpt_traceback-0.1.22.dist-info/RECORD
