Metadata-Version: 2.1
Name: gpt-traceback
Version: 0.1.22
Summary: Debug your exceptions with GPT
Home-page: https://github.com/franz101/gpt-exception
Author: Franz Krekeler
Author-email: filmfranz@findmeontwitter.com
Project-URL: Documentation, https://github.com/franz101/gpt-exception
Project-URL: Bug Reports, https://github.com/franz101/gpt-exception/issues
Project-URL: Source Code, https://github.com/franz101/gpt-exception
Keywords: gpt,jupyter,colab,traceback,debugging
Classifier: Development Status :: 5 - Production/Stable
Classifier: Intended Audience :: Developers
Classifier: Topic :: Software Development :: Build Tools
Classifier: Programming Language :: Python :: 3
Classifier: Programming Language :: Python :: 3.6
Classifier: Programming Language :: Python :: 3.7
Classifier: Programming Language :: Python :: 3.8
Classifier: Programming Language :: Python :: 3.9
Classifier: Programming Language :: Python :: 3 :: Only
Classifier: License :: OSI Approved :: MIT License
Classifier: Operating System :: OS Independent
Requires-Python: >=3.6
License-File: LICENSE
Requires-Dist: requests
Requires-Dist: rich
Requires-Dist: pygments
Provides-Extra: dev
Requires-Dist: check-manifest ; extra == 'dev'
